{
    "title": "B0038BZHHO",
    "id": "B0038BZHHO",
    "price": 0.0,
    "overview": {
        "_Specific_Uses_For_Product_": "Adhesive, bathroom, car, carpet, countertop, door, floor, oven, sink, tile, toilet, upholstery, wheel   See more",
        "_Item_Form_": "Wipe",
        "_Brand_": "Tub O' Towels",
        "_Surface_Recommendation_": "Tile,Carpet,Granite,Tub,Stone,Countertop",
        "_Special_Feature_": "Non Abrasive"
    },
    "discount": 0.0,
    "country": "US",
    "quantity": 0,
    "missOverview": false,
    "missDiscount": true,
    "missCountry": false,
    "missQuantity": false,
    "missPrice": false
}