{
    "title": "Gskyer Telescope, 70mm Aperture 400mm AZ Mount Astronomical Refracting Telescope for Kids Beginners - Travel Telescope with Carry Bag, Phone Adapter and Wireless Remote",
    "id": "B081RJ8DW1",
    "price": 99.99,
    "overview": {
        "_Brand_": "Gskyer",
        "_Eye_Piece_Lens_Description_": "Barlow",
        "_Objective_Lens_Diameter_": "70 Millimeters",
        "_Telescope_Mount_Description_": "Altazimuth Mount",
        "_Item_Weight_": "5.71 Pounds",
        "_Lens_Coating_Description_": "Fully Coated",
        "_Focal_Length_Description_": "400 millimeters"
    },
    "discount": 30.0,
    "country": "US",
    "quantity": 32,
    "missOverview": false,
    "missDiscount": false,
    "missCountry": false,
    "missQuantity": false,
    "missPrice": false
}