{"title": "LaView Security Cameras 4pcs, Home Security Camera Indoor 1080P, Wi-Fi Cameras for Pet, Motion Detection, Two-Way Audio, Night Vision, Works with Alexa, iOS & Android & Web Access", "id": "B08JB4LZ19", "price": 89.98, "overview": {"_Indoor/Outdoor_Usage_": "Indoor", "_Brand_": "LaView", "_Connectivity_Technology_": "Wireless", "_Recommended_Uses_For_Product_": "Surveillance", "_Room_Type_": "Office, Kitchen, Living Room"}, "discount": -1.0, "country": "US", "quantity": 30, "missOverview": false, "missDiscount": true, "missCountry": false, "missQuantity": false, "missPrice": false}