{
    "title": "Nighttime Baby Diapers Size 3, 66 Ct, Huggies Overnites",
    "id": "B08QRTWRZ6",
    "price": 26.97,
    "overview": {
        "_Size_": "Size 3 (66 Count)",
        "_Recommended_Uses_For_Product_": "Baby Diapers",
        "_Age_Range_(Description)_": "Baby",
        "_Brand_": "HUGGIES",
        "_Color_": "Multi-color"
    },
    "discount": 2.18,
    "country": "US",
    "quantity": 4,
    "missOverview": false,
    "missDiscount": false,
    "missCountry": false,
    "missQuantity": false,
    "missPrice": false
}